svgecko/__init__.py
svgecko/example.py
svgecko/svg.py
svgecko/svg_path.py
svgecko/utils.py
svgecko/resources/cross.svg
svgecko/resources/python-logo.svg
tests/__init__.py
tests/test_svg.py
svgecko-0.3.4.dist-info/METADATA
svgecko-0.3.4.dist-info/WHEEL
svgecko-0.3.4.dist-info/top_level.txt
svgecko-0.3.4.dist-info/RECORD
