Metadata-Version: 2.1
Name: svgecko
Version: 0.3.4
Summary: Lightweight library for arbitrary geometric SVG transformations
Author: Josef Ondrej
Author-email: josef.ondrej@outlook.com
Requires-Dist: lxml
Requires-Dist: pillow
Requires-Dist: cairosvg
Requires-Dist: pytest
Requires-Dist: numpy
